{"doc":" 项目技能管理控制器。\n\n <p>管理项目级技能的启用和查询，路径前缀为 {@code /api/projects/{projectId}/skills}。</p>\n","fields":[],"enumConstants":[],"methods":[{"name":"enable","paramTypes":["java.lang.Long","java.lang.Long"],"doc":" 为项目启用技能。\n\n @param projectId 项目ID\n @param skillId   技能ID\n @return 项目技能关联实体\n"},{"name":"list","paramTypes":["java.lang.Long"],"doc":" 查询项目已启用的技能列表。\n\n @param projectId 项目ID\n @return 项目技能关联列表\n"}],"constructors":[{"name":"<init>","paramTypes":["com.aiplatform.backend.service.SkillService"],"doc":" 构造函数，注入技能业务服务。\n\n @param skillService 技能业务服务\n"}]}