{"doc":" JWT 认证拦截器。\n\n <p>对每个请求执行以下流程：\n <ol>\n   <li>从 {@code Authorization: Bearer <token>} 头中提取 JWT</li>\n   <li>验证签名和有效期</li>\n   <li>从 DB 查询用户最新的 {@code role_id}，再通过 {@code roles.code} 获取角色编码</li>\n   <li>通过 {@link RbacService} 加载该角色的权限点集合</li>\n   <li>将 {@link AuthContext.AuthPrincipal} 写入 {@link AuthContext}（ThreadLocal）</li>\n </ol>\n\n <p>白名单路径（登录、刷新 Token、Swagger 文档等）跳过校验，直接放行。</p>\n","fields":[{"name":"WHITE_LIST","doc":"不需要认证的路径前缀 "}],"enumConstants":[],"methods":[],"constructors":[]}