{"doc":" 平台凭证业务服务。\n\n <p>提供凭证的创建（含密钥生成和 SHA-256 哈希）、按用户查询、吊销等操作。\n 密钥格式为 {@code plt_{uid}_{random}_{checksum}}，创建时仅返回一次明文。</p>\n\n <h3>凭证模型：一人一证，跨项目共用</h3>\n <p>每名成员在平台拥有唯一一张凭证（uk_platform_credentials_user 唯一索引约束），\n 邀请时自动生成。凭证跨项目复用，无需为不同项目单独申请。</p>\n","fields":[],"enumConstants":[],"methods":[{"name":"create","paramTypes":["com.aiplatform.backend.dto.CreatePlatformCredentialRequest"],"doc":" 创建平台凭证，生成密钥并以 SHA-256 哈希存储。\n\n <p>自动初始化个人月度 Token 配额字段（双池之一）。\n 若请求未指定配额参数，使用平台默认值：上限 200K、阈值 80%、策略 BLOCK。</p>\n\n @param request 创建请求\n @return 包含明文密钥的创建响应（明文仅此一次展示）\n"},{"name":"listByUserId","paramTypes":["java.lang.Long"],"doc":"按用户 ID 查询凭证（每用户唯一一条）。 "},{"name":"getByUserId","paramTypes":["java.lang.Long"],"doc":"按用户 ID 查询唯一凭证，不存在时返回 null。 "},{"name":"revoke","paramTypes":["java.lang.Long","java.lang.String"],"doc":" 吊销凭证，设置状态为 REVOKED 并记录原因。\n\n @param id     凭证 ID\n @param reason 吊销原因\n"},{"name":"getByIdOrThrow","paramTypes":["java.lang.Long"],"doc":"根据 ID 查询凭证，不存在则抛出异常。 "}],"constructors":[]}